<markup>
<entry>
<id>1</id>
<offset>0</offset>
<length>7</length>
<class>AAA_Estimate_Person</class>
<attribute>
<name>Canonical</name>
<value>ГАЛУШКА</value>
</attribute>
</entry>
<entry>
<id>2</id>
<offset>169</offset>
<length>17</length>
<class>AAA_Estimate_Person</class>
<attribute>
<name>Canonical</name>
<value>АЛЕКСАНДР ГАЛУШКА</value>
</attribute>
</entry>
<entry>
<id>3</id>
<offset>326</offset>
<length>7</length>
<class>AAA_Estimate_Person</class>
<attribute>
<name>Canonical</name>
<value>ГАЛУШКА</value>
</attribute>
</entry>
<entry>
<id>4</id>
<offset>462</offset>
<length>17</length>
<class>AAA_Estimate_Person</class>
<attribute>
<name>Canonical</name>
<value>АЛЕКСАНДР ГАЛУШКА</value>
</attribute>
</entry>
<entry>
<id>5</id>
<offset>564</offset>
<length>12</length>
<class>AAA_Estimate_Person</class>
<attribute>
<name>Canonical</name>
<value>ВИКТОР ИШАЕВ</value>
</attribute>
</entry>
<entry>
<id>6</id>
<offset>666</offset>
<length>7</length>
<class>AAA_Estimate_Person</class>
<attribute>
<name>Canonical</name>
<value>ГАЛУШКА</value>
</attribute>
</entry>
<entry>
<id>7</id>
<offset>902</offset>
<length>7</length>
<class>AAA_Estimate_Person</class>
<attribute>
<name>Canonical</name>
<value>ГАЛУШКА</value>
</attribute>
</entry>
<entry>
<id>8</id>
<offset>947</offset>
<length>15</length>
<class>AAA_Estimate_Person</class>
<attribute>
<name>Canonical</name>
<value>ЮРИЙ ТРУТНЕВ</value>
</attribute>
</entry>
<entry>
<id>9</id>
<offset>990</offset>
<length>14</length>
<class>AAA_Estimate_Person</class>
<attribute>
<name>Canonical</name>
<value>ВИКТОР ИШАЕВ</value>
</attribute>
</entry>
<entry>
<id>10</id>
<offset>1012</offset>
<length>5</length>
<class>AAA_Estimate_Person</class>
<attribute>
<name>Canonical</name>
<value>ИШАЕВ</value>
</attribute>
</entry>
</markup>
