<markup>
<entry>
<id>1</id>
<offset>0</offset>
<length>8</length>
<class>AAA_Estimate_Person</class>
<attribute>
<name>Canonical</name>
<value>МЕДВЕДЕВ</value>
</attribute>
</entry>
<entry>
<id>2</id>
<offset>53</offset>
<length>16</length>
<class>AAA_Estimate_Person</class>
<attribute>
<name>Canonical</name>
<value>ДМИТРИЙ МЕДВЕДЕВ</value>
</attribute>
</entry>
<entry>
<id>3</id>
<offset>258</offset>
<length>16</length>
<class>AAA_Estimate_Person</class>
<attribute>
<name>Canonical</name>
<value>ВИКТОР БЕРДНИКОВ</value>
</attribute>
</entry>
<entry>
<id>4</id>
<offset>342</offset>
<length>16</length>
<class>AAA_Estimate_Person</class>
<attribute>
<name>Canonical</name>
<value>НИКОЛАЙ МИХАЙЛОВ</value>
</attribute>
</entry>
<entry>
<id>5</id>
<offset>392</offset>
<length>11</length>
<class>AAA_Estimate_Person</class>
<attribute>
<name>Canonical</name>
<value>ЯКОВ СТАХОВ</value>
</attribute>
</entry>
<entry>
<id>6</id>
<offset>453</offset>
<length>17</length>
<class>AAA_Estimate_Person</class>
<attribute>
<name>Canonical</name>
<value>БОРИС ТИМОНИЧЕНКО</value>
</attribute>
</entry>
<entry>
<id>7</id>
<offset>526</offset>
<length>10</length>
<class>AAA_Estimate_Person</class>
<attribute>
<name>Canonical</name>
<value>ОЛЕГ ХОТИН</value>
</attribute>
</entry>
<entry>
<id>8</id>
<offset>583</offset>
<length>14</length>
<class>AAA_Estimate_Person</class>
<attribute>
<name>Canonical</name>
<value>ВИКТОР БУЛУШЕВ</value>
</attribute>
</entry>
<entry>
<id>9</id>
<offset>648</offset>
<length>11</length>
<class>AAA_Estimate_Person</class>
<attribute>
<name>Canonical</name>
<value>ЮРИЙ ГОРЛОВ</value>
</attribute>
</entry>
<entry>
<id>10</id>
<offset>727</offset>
<length>18</length>
<class>AAA_Estimate_Person</class>
<attribute>
<name>Canonical</name>
<value>НИКОЛАЙ ГУДОЖНИКОВ</value>
</attribute>
</entry>
<entry>
<id>11</id>
<offset>781</offset>
<length>17</length>
<class>AAA_Estimate_Person</class>
<attribute>
<name>Canonical</name>
<value>АНАТОЛИЙ ЖУРАВЛЕВ</value>
</attribute>
</entry>
<entry>
<id>12</id>
<offset>835</offset>
<length>15</length>
<class>AAA_Estimate_Person</class>
<attribute>
<name>Canonical</name>
<value>НИКОЛАЙ ЛАРЬКОВ</value>
</attribute>
</entry>
<entry>
<id>13</id>
<offset>908</offset>
<length>5</length>
<class>AAA_Estimate_Person</class>
<attribute>
<name>Canonical</name>
<value>ХОТИН</value>
</attribute>
</entry>
<entry>
<id>14</id>
<offset>915</offset>
<length>6</length>
<class>AAA_Estimate_Person</class>
<attribute>
<name>Canonical</name>
<value>ГОРЛОВ</value>
</attribute>
</entry>
<entry>
<id>15</id>
<offset>923</offset>
<length>10</length>
<class>AAA_Estimate_Person</class>
<attribute>
<name>Canonical</name>
<value>ГУДОЖНИКОВ</value>
</attribute>
</entry>
<entry>
<id>16</id>
<offset>936</offset>
<length>8</length>
<class>AAA_Estimate_Person</class>
<attribute>
<name>Canonical</name>
<value>ЖУРАВЛЕВ</value>
</attribute>
</entry>
<entry>
<id>17</id>
<offset>992</offset>
<length>6</length>
<class>AAA_Estimate_Person</class>
<attribute>
<name>Canonical</name>
<value>СТАХОВ</value>
</attribute>
</entry>
<entry>
<id>18</id>
<offset>1000</offset>
<length>11</length>
<class>AAA_Estimate_Person</class>
<attribute>
<name>Canonical</name>
<value>ТИМОНИЧЕНКО</value>
</attribute>
</entry>
<entry>
<id>19</id>
<offset>1013</offset>
<length>7</length>
<class>AAA_Estimate_Person</class>
<attribute>
<name>Canonical</name>
<value>БУЛУШЕВ</value>
</attribute>
</entry>
<entry>
<id>20</id>
<offset>1023</offset>
<length>7</length>
<class>AAA_Estimate_Person</class>
<attribute>
<name>Canonical</name>
<value>ЛАРЬКОВ</value>
</attribute>
</entry>
<entry>
<id>21</id>
<offset>1077</offset>
<length>9</length>
<class>AAA_Estimate_Person</class>
<attribute>
<name>Canonical</name>
<value>БЕРДНИКОВ</value>
</attribute>
</entry>
<entry>
<id>22</id>
<offset>1159</offset>
<length>8</length>
<class>AAA_Estimate_Person</class>
<attribute>
<name>Canonical</name>
<value>МИХАЙЛОВ</value>
</attribute>
</entry>
<entry>
<id>23</id>
<offset>1247</offset>
<length>9</length>
<class>AAA_Estimate_Person</class>
<attribute>
<name>Canonical</name>
<value>МЕДВЕДЕВ</value>
</attribute>
</entry>
</markup>
